timonctl/__init__.py
timonctl/blueprint.py
timonctl/client.py
timonctl/common.py
timonctl/deployment.py
timonctl/enums.py
timonctl/environment.py
timonctl/exceptions.py
timonctl/flow.py
timonctl/main.py
timonctl/models.py
timonctl/project.py
timonctl/template.py
timonctl/schemas/__init__.py
timonctl/schemas/schema.blueprint.yaml
timonctl/schemas/schema.config.yaml
timonctl/schemas/schema.environment.yaml
timonctl/schemas/schema.flow.yaml
timonctl/schemas/schema.template.yaml
timonctl-0.0.12.dist-info/AUTHORS
timonctl-0.0.12.dist-info/LICENSE
timonctl-0.0.12.dist-info/METADATA
timonctl-0.0.12.dist-info/WHEEL
timonctl-0.0.12.dist-info/entry_points.txt
timonctl-0.0.12.dist-info/pbr.json
timonctl-0.0.12.dist-info/top_level.txt
timonctl-0.0.12.dist-info/RECORD
