Metadata-Version: 2.1
Name: timonctl
Version: 0.0.12
Summary: CLI for Timon
Home-page: https://github.com/timontech/timonctl
Author: OSISM GmbH
Author-email: info@osism.tech
Classifier: Development Status :: 3 - Alpha
Classifier: Environment :: Console
Classifier: Intended Audience :: Developers
Classifier: Intended Audience :: Information Technology
Classifier: License :: OSI Approved :: Apache Software License
Classifier: Operating System :: OS Independent
Classifier: Programming Language :: Python
Classifier: Programming Language :: Python :: 3 :: Only
Classifier: Programming Language :: Python :: 3
Classifier: Programming Language :: Python :: 3.8
Classifier: Programming Language :: Python :: 3.9
Classifier: Programming Language :: Python :: 3.10
Requires-Python: >=3.8
License-File: LICENSE
License-File: AUTHORS
Requires-Dist: appdirs (==1.4.4)
Requires-Dist: certifi (==2022.9.24)
Requires-Dist: charset-normalizer (==2.1.1)
Requires-Dist: click (==8.1.3)
Requires-Dist: colorama (==0.4.5)
Requires-Dist: commonmark (==0.9.1)
Requires-Dist: dynaconf (==3.1.11)
Requires-Dist: idna (==3.4)
Requires-Dist: loguru (==0.6.0)
Requires-Dist: pbr (==5.11.0)
Requires-Dist: pydantic (==1.10.2)
Requires-Dist: Pygments (==2.13.0)
Requires-Dist: PyYAML (==6.0)
Requires-Dist: requests (==2.28.1)
Requires-Dist: rich (==12.6.0)
Requires-Dist: shellingham (==1.5.0)
Requires-Dist: tabulate (==0.9.0)
Requires-Dist: typer (==0.6.1)
Requires-Dist: typing-extensions (==4.4.0)
Requires-Dist: urllib3 (==1.26.12)
Requires-Dist: yamale (==4.0.4)
